foxai/__init__.py
foxai/array_utils.py
foxai/callbacks/__init__.py
foxai/callbacks/wandb_callback.py
foxai/cli/__init__.py
foxai/cli/config_model.py
foxai/cli/experiment_update.py
foxai/context_manager.py
foxai/explainer/__init__.py
foxai/explainer/base_explainer.py
foxai/explainer/computer_vision/__init__.py
foxai/explainer/computer_vision/algorithm/__init__.py
foxai/explainer/computer_vision/algorithm/conductance.py
foxai/explainer/computer_vision/algorithm/deconv.py
foxai/explainer/computer_vision/algorithm/deeplift.py
foxai/explainer/computer_vision/algorithm/deeplift_shap.py
foxai/explainer/computer_vision/algorithm/gradcam.py
foxai/explainer/computer_vision/algorithm/gradient_shap.py
foxai/explainer/computer_vision/algorithm/guided_backprop.py
foxai/explainer/computer_vision/algorithm/input_x_gradient.py
foxai/explainer/computer_vision/algorithm/integrated_gradients.py
foxai/explainer/computer_vision/algorithm/lrp.py
foxai/explainer/computer_vision/algorithm/noise_tunnel.py
foxai/explainer/computer_vision/algorithm/occlusion.py
foxai/explainer/computer_vision/algorithm/saliency.py
foxai/explainer/computer_vision/model_utils.py
foxai/explainer/computer_vision/object_detection/__init__.py
foxai/explainer/computer_vision/object_detection/base_object_detector.py
foxai/explainer/computer_vision/object_detection/types.py
foxai/explainer/computer_vision/object_detection/utils.py
foxai/logger.py
foxai/visualizer.py
foxai-0.6.0.dist-info/entry_points.txt
foxai-0.6.0.dist-info/LICENSE
foxai-0.6.0.dist-info/WHEEL
foxai-0.6.0.dist-info/METADATA
foxai-0.6.0.dist-info/RECORD
