Metadata-Version: 2.1
Name: foxai
Version: 0.6.0
Summary: Model Interpretability for PyTorch.
Home-page: https://github.com/softwaremill/FoXAI
License: Apache-2.0
Keywords: Model Interpretability,XAI,explainable AI,Model Understanding,Feature Importance,PyTorch
Author: ReasonField Lab Team
Maintainer: Adam Jan Kaczmarek
Maintainer-email: adam.kaczmarek@reasonfieldlab.com
Requires-Python: >=3.7.2,<3.11
Classifier: Development Status :: 3 - Alpha
Classifier: Intended Audience :: Developers
Classifier: Intended Audience :: Education
Classifier: Intended Audience :: Science/Research
Classifier: License :: OSI Approved :: Apache Software License
Classifier: Programming Language :: Python :: 3
Classifier: Programming Language :: Python :: 3.8
Classifier: Programming Language :: Python :: 3.9
Classifier: Programming Language :: Python :: 3.10
Classifier: Topic :: Scientific/Engineering
Requires-Dist: captum (>=0.5.0,<1.0.0)
Requires-Dist: hydra-core (>=1.3.1,<2.0.0)
Requires-Dist: numpy (>=1.21.4,<2.0.0)
Requires-Dist: opencv-python (>=4.7.0.68,<5.0.0)
Requires-Dist: pandas (>=1.1.0,<2.0.0)
Requires-Dist: pytorch-lightning (>=1.5.0,<2.0.0)
Requires-Dist: seaborn (>=0.12.2,<0.13.0)
Requires-Dist: single-source (>=0.3.0,<1.0.0)
Requires-Dist: torch (>=1.12.1,<2.0.0)
Requires-Dist: wandb (>=0.13.7,<1.0.0)
Project-URL: Bug Tracker, https://github.com/softwaremill/foxai/issues
Project-URL: Documentation, https://softwaremill.github.io/FoXAI/
Project-URL: Repository, https://github.com/softwaremill/FoXAI
